CollinImports/IdGeneratorRedisKubernetes.py
CollinImports/__init__.py
CollinImports-0.0.4.dist-info/LICENSE
CollinImports-0.0.4.dist-info/METADATA
CollinImports-0.0.4.dist-info/WHEEL
CollinImports-0.0.4.dist-info/top_level.txt
CollinImports-0.0.4.dist-info/RECORD
